stop_utils/__init__.py
stop_utils/cli.py
stop_utils/converters.py
stop_utils/types.py
stop_utils/visualization.py
stop_utils/wfe_analysis.py
stop_utils/zemax/__init__.py
stop_utils/zemax/wavefront_extractor.py
stop_utils/zemax/zmx_batch_processor.py
stop_utils/zemax/zmx_boilerplate.py
stop_utils-0.6.2.dist-info/LICENSE
stop_utils-0.6.2.dist-info/METADATA
stop_utils-0.6.2.dist-info/WHEEL
stop_utils-0.6.2.dist-info/entry_points.txt
stop_utils-0.6.2.dist-info/RECORD
