Metadata-Version: 2.3
Name: stop-utils
Version: 0.6.2
Summary: Utilities for analyzing wavefront error data
License: BSD 3-Clause
Keywords: optics,wavefront,analysis,polynomials,paos,zernike,Ariel
Author: Andrea Bocchieri
Author-email: andrea.bocchieri@uniroma1.it
Requires-Python: >=3.10,<3.14
Classifier: Development Status :: 4 - Beta
Classifier: Intended Audience :: Science/Research
Classifier: License :: Other/Proprietary License
Classifier: Programming Language :: Python :: 3
Classifier: Programming Language :: Python :: 3.10
Classifier: Programming Language :: Python :: 3.11
Classifier: Programming Language :: Python :: 3.12
Classifier: Programming Language :: Python :: 3.13
Classifier: Topic :: Scientific/Engineering :: Astronomy
Classifier: Topic :: Scientific/Engineering :: Physics
Requires-Dist: loguru (>=0.7.2,<0.8.0)
Requires-Dist: matplotlib (>=3.7.0,<4.0.0)
Requires-Dist: numpy (>=1.24.0,<2.0.0)
Requires-Dist: paos (>=1.2.8,<2.0.0)
Requires-Dist: photutils (>=1.7.0,<2.0.0)
Requires-Dist: pythonnet (>=3.0.5,<4.0.0)
Requires-Dist: rich (>=14.0.0,<15.0.0)
Requires-Dist: scikit-image (>=0.25.0,<0.26.0)
Requires-Dist: typer (>=0.9.0,<0.10.0)
Project-URL: Documentation, https://stop-utils.readthedocs.io
Project-URL: Homepage, https://github.com/arielmission-space/stop-utils
Project-URL: Repository, https://github.com/arielmission-space/stop-utils
